gtredactkit/__init__.py
gtredactkit/__main__.py
gtredactkit/common_jobs.py
gtredactkit/core_redactor.py
gtredactkit/custom_redactor.py
gtredactkit/gtredactkit.py
gtredactkit/identifiers.py
gtredactkit/unredact.py
gtredactkit-0.0.8.dist-info/entry_points.txt
gtredactkit-0.0.8.dist-info/LICENSE
gtredactkit-0.0.8.dist-info/WHEEL
gtredactkit-0.0.8.dist-info/METADATA
gtredactkit-0.0.8.dist-info/RECORD
