Metadata-Version: 2.1
Name: gtredactkit
Version: 0.0.8
Summary: Python cli tool to redact sensitive data
Home-page: https://github.com/brootware/gtredactkit
License: MIT
Author: brootware
Author-email: brootware@outlook.com
Requires-Python: >=3.7,<4.0
Classifier: Development Status :: 5 - Production/Stable
Classifier: Intended Audience :: Information Technology
Classifier: License :: OSI Approved :: MIT License
Classifier: Operating System :: OS Independent
Classifier: Programming Language :: Python :: 3
Classifier: Programming Language :: Python :: 3.10
Classifier: Programming Language :: Python :: 3.7
Classifier: Programming Language :: Python :: 3.8
Classifier: Programming Language :: Python :: 3.9
Classifier: Topic :: Internet :: Log Analysis
Classifier: Topic :: Security
Classifier: Topic :: Text Processing :: General
Project-URL: Repository, https://github.com/brootware/gtredactkit
